{
  "generator-jhipster": {
    "applicationType": "monolith",
    "gitHubOrganization": "sandeshpawar",
    "baseName": "helloWorld",
    "packageName": "io.github.jhipster.application",
    "serverPort": 8080,
    "serviceDiscoveryType": false,
    "authenticationType": "jwt",
    "uaaBaseName": "../uaa",
    "cacheProvider": "ehcache",
    "enableHibernateCache": true,
    "clusteredHttpSession": false,
    "websocket": "spring-websocket",
    "databaseType": "sql",
    "devDatabaseType": "h2Disk",
    "prodDatabaseType": "mysql",
    "searchEngine": "elasticsearch",
    "enableSwaggerCodegen": "true",
    "messageBroker": false,
    "buildTool": "maven",
    "enableSocialSignIn": false,
    "useSass": false,
    "clientPackageManager": "yarn",
    "testFrameworks": [],
    "enableTranslation": false,
    "nativeLanguage": "en",
    "languages": [
      "en"
    ],
    "clientFramework": "angularX",
    "jhipsterVersion": "4.13.1",
    "packageFolder": "io/github/jhipster/application",
    "jwtSecretKey": "fb9e50550d4a71ea39ebf24f39eab882b71e9195",
    "jhiPrefix": "jhi"
  }
}